README
setup.py
dsmsfilepackager/__init__.py
dsmsfilepackager/exceptions.py
dsmsfilepackager/filepackage.py
dsmsfilepackager.egg-info/PKG-INFO
dsmsfilepackager.egg-info/SOURCES.txt
dsmsfilepackager.egg-info/dependency_links.txt
dsmsfilepackager.egg-info/requires.txt
dsmsfilepackager.egg-info/top_level.txt