Metadata-Version: 1.0
Name: dsmsfilepackager
Version: 0.1.10
Summary: UNKNOWN
Home-page: http://bitbucket.org/dsms/dsmsfilepackager/
Author: Chris Horsley
Author-email: chris.horsley@csirtfoundry.com
License: LICENSE.txt
Platform: UNKNOWN
